{"id":"76fe10c745","source":"hn","title":"Apple Container 1.0 Released as a Native Docker Alternative for macOS","abstract":"No detailed description yet. This tool is pending review.","abstract_zh":"暂无详细描述，该工具正在审核中。","url":"https://linuxiac.com/apple-container-1-0-released-as-a-native-docker-alternative-for-macos/","score":2,"captured_at":"2026-07-05 08:00:25","category":["dev-tool"],"scene":"xitong","region":"global","roles":["developer"],"data_tags":["fresh","__garbage__"],"reason":"HN hot (2 pts) - AIbounty hunted","grade":"B","grade_label":"有推荐·可用","_quality_flag":"garbage"}