{"source":"nav_hunter","title":"多面鹅","abstract":"多面鹅 is an AI tool that solves a specific problem well. Whether it is boosting productivity or enabling something new, it is worth a look.","url":"https://ai-bot.cn/offergoose/","score":1,"id":"多面鹅","category":["uncategorized"],"data_tags":["recent"],"captured_at":"2026-06-21 16:11:46","grade_label":"普通·待激活","abstract_zh":"来试试 **MultiGoose** 吧！这货简直就是效率的救星！当你在写周报时，自动整理和分类功能简直让人怀疑人生是怎么度过的；调Bug时，智能代码审查直接让你从枯燥中解放出来。多面鹅，一个能帮你变废为宝的小帮手！","price_model":"unknown","grade":"C","region":"cn"}