{"source":"nav_hunter","title":"刺鸟配音","abstract":"刺鸟配音 may be niche, but it solves its target problem with focus and precision. In the fast-moving AI space, specialized tools often outperform general platforms.","url":"https://ai-bot.cn/sites/16136.html","score":1,"id":"刺鸟配音","category":["uncategorized"],"data_tags":["recent"],"captured_at":"2026-06-21 16:11:46","grade_label":"普通·待激活","abstract_zh":"伙儿！来个新鲜事儿——试试**StirBird Voice**吧！这货简直是个效率小能手，写周报时，它能帮你快速生成专业配音；调Bug时，让你的代码声情并茂。比那些死板的文字工具强多了，因为它不仅能节省你的时间，还能让汇报和解释变得更生动有趣！来试试，你的工作效率绝对能瞬间up up！","price_model":"unknown","grade":"C","region":"cn"}