{"source":"nav_hunter","title":"笔格设计","abstract":"笔格设计 handles image generation, video creation and 3D modeling from text descriptions. Built for creators who want results without the software learning curve.","url":"https://ai-bot.cn/sites/14748.html","score":1,"id":"笔格设计","category":["media"],"data_tags":["scene-image","design-tools","recent"],"captured_at":"2026-06-21 16:11:46","grade_label":"普通·待激活","abstract_zh":"你们有没有在写周报或调试代码时感到头疼？那就试试 **Pen格设计** 吧！它不仅帮你一键生成美观的图表和报告，还能自动整理你的思路。相比那些笨拙的小工具，Pen格设计简直就是效率提升的秘密武器！比如，当你写完一堆Bug记录，直接扔给它，立刻就给你排版得整整齐齐，简直是加班党福音！","price_model":"unknown","grade":"C","region":"cn"}