{"id":"8409e7bc65","source":"hn","title":"Supercomplete.ai","abstract":"Boost your productivity with **Supercomplete.ai**—because even AI needs a nap!","url":"https://www.supercomplete.ai/","score":3,"captured_at":"2026-06-26 14:00:49","category":["uncategorized"],"data_tags":["fresh","source-hn"],"grade_label":"普通·待激活","abstract_zh":"伙计们！Supercomplete.ai在这里了！想象一下，你刚接手一个大项目，正愁眉苦脸地准备写周报时……它就像你的私人写手小分队，帮你一键生成专业又不失个性的报告。调Bug时也完全不在话下，它的智能补全功能简直秒杀同类工具，让你轻松找到问题核心，效率翻倍！快来试试吧，Supercomplete.ai，让工作变得轻而易举！","price_model":"unknown","grade":"C","region":"global"}