{"source":"nav_hunter","title":"OmniBox小黑","abstract":"OmniBox小黑 is an AI tool that solves a specific problem well. Whether it is boosting productivity or enabling something new, it is worth a look.","url":"https://ai-bot.cn/sites/64396.html","score":1,"id":"omnibox小黑","category":["uncategorized"],"data_tags":["recent"],"captured_at":"2026-06-21 16:11:46","grade_label":"普通·待激活","abstract_zh":"快来试试这个神器——**OmniBox小黑**！写周报时再也不怕数据乱了套，它能一键抓取关键指标；调Bug时更是得心应手，代码搜索秒变顺滑高手。关键是操作超简单，不带任何学习成本，简直就是提升效率的的秘密武器！快来加入它的行列吧！","price_model":"unknown","grade":"C","region":"cn"}